{
    "name": "casaos_debugger",
    "ui": {
        "name": "casaos_debugger",
        "title": {
          "en_us": "Debugger"
        },
        "prefetch": true,
        "show": true,
        "entry": "/modules/casaos_debugger/index.html",
        "icon": "/modules/casaos_debugger/logo.webp",
        "description": "Debug Tool for CasaOS and ZimaOS",
        "formality": {
          "type": "newtab",
          "props": {
            "width": "100vh",
            "height": "100vh",
            "hasModalCard": true,
            "animation": "zoom-in"
          }
        }
    },
    "services": [
        {
            "name": "casaos-debugger"
        }
    ]     
}